kg_engine/__init__.py
kg_engine/config/__init__.py
kg_engine/config/neo4j_config.py
kg_engine/config/neo4j_schema.py
kg_engine/core/__init__.py
kg_engine/core/engine.py
kg_engine/llm/__init__.py
kg_engine/llm/llm_interface.py
kg_engine/models/__init__.py
kg_engine/models/classifier_map.py
kg_engine/models/models.py
kg_engine/storage/__init__.py
kg_engine/storage/graph_db.py
kg_engine/storage/graphdb_examples.py
kg_engine/storage/storage_documentation.md
kg_engine/storage/vector_store.py
kg_engine/utils/__init__.py
kg_engine/utils/classifier_detector.py
kg_engine/utils/date_parser.py
kg_engine/utils/graph_query_optimizer.py
kg_engine/utils/neo4j_optimizer.py
kg_engine_v2-2.3.1.dist-info/METADATA
kg_engine_v2-2.3.1.dist-info/WHEEL
kg_engine_v2-2.3.1.dist-info/RECORD
