Metadata-Version: 2.4
Name: kg-engine-v2
Version: 2.3.1
Summary: Advanced Knowledge Graph Engine with semantic search and temporal tracking
Project-URL: Homepage, https://github.com/dasein108/kg_semantic
Project-URL: Repository, https://github.com/dasein108/kg_semantic.git
Project-URL: Issues, https://github.com/dasein108/kg_semantic/issues
Author-email: KG/Semantic Engine <acidpictures@gmail.com>
Requires-Python: >=3.8
Requires-Dist: dateparser>=1.1.0
Requires-Dist: llama-index-vector-stores-neo4jvector>=0.3.0
Requires-Dist: llama-index>=0.10.0
Requires-Dist: neo4j>=5.0.0
Requires-Dist: numpy>=1.24.0
Requires-Dist: openai>=1.0.0
Requires-Dist: python-dotenv>=1.0.0
Requires-Dist: sentence-transformers>=2.2.0
Provides-Extra: dev
Requires-Dist: black>=23.0.0; extra == 'dev'
Requires-Dist: flake8>=6.0.0; extra == 'dev'
Requires-Dist: mypy>=1.0.0; extra == 'dev'
Requires-Dist: pytest>=7.0.0; extra == 'dev'
